[
  {
    "id": "ev-google-trends-0",
    "lat": 54.5,
    "lng": -2,
    "category": "google-trends",
    "severity": "minor",
    "timestamp": "2025-11-13T01:27:08.289Z",
    "title": "SEARCH SPIKE: \"flood insurance\"",
    "locationName": "Regional | County | Constituency Placeholder",
    "source": "Google Trends",
    "sourceUrl": "#",
    "assessment": {
      "confidenceLabel": "High",
      "confidenceColor": "#4ade80",
      "confidence": 88,
      "justification": "Automated assessment based on multi-source impact analysis and framework criteria.",
      "sourceLabel": "Google Trends",
      "sourceReliability": "Unofficial",
      "intelligenceType": "Direct",
      "corroborated": true,
      "startTiming": "14:00",
      "endTiming": "",
      "synthesis": "Evidence shows localized environmental stress and reported infrastructure failure based on emerging reports.",
      "confidenceStatement": "This is a High confidence assessment."
    }
  },
  {
    "id": "ev-google-trends-1",
    "lat": 54.5,
    "lng": -2,
    "category": "google-trends",
    "severity": "minor",
    "timestamp": "2025-11-14T15:04:47.256Z",
    "title": "SEARCH SPIKE: \"water pumps\"",
    "locationName": "Regional | County | Constituency Placeholder",
    "source": "Google Trends",
    "sourceUrl": "#",
    "assessment": {
      "confidenceLabel": "High",
      "confidenceColor": "#4ade80",
      "confidence": 87,
      "justification": "Automated assessment based on multi-source impact analysis and framework criteria.",
      "sourceLabel": "Google Trends",
      "sourceReliability": "Unofficial",
      "intelligenceType": "Direct",
      "corroborated": true,
      "startTiming": "16:00",
      "endTiming": "",
      "synthesis": "Evidence shows localized environmental stress and reported infrastructure failure based on emerging reports.",
      "confidenceStatement": "This is a High confidence assessment."
    }
  },
  {
    "id": "ev-google-trends-2",
    "lat": 54.5,
    "lng": -2,
    "category": "google-trends",
    "severity": "significant",
    "timestamp": "2025-11-14T09:48:13.381Z",
    "title": "SEARCH SPIKE: \"sandbags\"",
    "locationName": "Regional | County | Constituency Placeholder",
    "source": "Google Trends",
    "sourceUrl": "#",
    "assessment": {
      "confidenceLabel": "High",
      "confidenceColor": "#4ade80",
      "confidence": 95,
      "justification": "Automated assessment based on multi-source impact analysis and framework criteria.",
      "sourceLabel": "Google Trends",
      "sourceReliability": "Unofficial",
      "intelligenceType": "Direct",
      "corroborated": true,
      "startTiming": "17:00",
      "endTiming": "",
      "synthesis": "Evidence shows localized environmental stress and reported infrastructure failure based on emerging reports.",
      "confidenceStatement": "This is a High confidence assessment."
    }
  },
  {
    "id": "ev-google-trends-3",
    "lat": 54.5,
    "lng": -2,
    "category": "google-trends",
    "severity": "significant",
    "timestamp": "2025-11-14T13:18:47.842Z",
    "title": "SEARCH SPIKE: \"local rescue\"",
    "locationName": "Regional | County | Constituency Placeholder",
    "source": "Google Trends",
    "sourceUrl": "#",
    "assessment": {
      "confidenceLabel": "High",
      "confidenceColor": "#4ade80",
      "confidence": 95,
      "justification": "Automated assessment based on multi-source impact analysis and framework criteria.",
      "sourceLabel": "Google Trends",
      "sourceReliability": "Unofficial",
      "intelligenceType": "Direct",
      "corroborated": true,
      "startTiming": "15:00",
      "endTiming": "",
      "synthesis": "Evidence shows localized environmental stress and reported infrastructure failure based on emerging reports.",
      "confidenceStatement": "This is a High confidence assessment."
    }
  },
  {
    "id": "ev-google-trends-4",
    "lat": 54.5,
    "lng": -2,
    "category": "google-trends",
    "severity": "minor",
    "timestamp": "2025-11-14T08:37:02.363Z",
    "title": "SEARCH SPIKE: \"flood insurance\"",
    "locationName": "Regional | County | Constituency Placeholder",
    "source": "Google Trends",
    "sourceUrl": "#",
    "assessment": {
      "confidenceLabel": "Medium",
      "confidenceColor": "#facc15",
      "confidence": 80,
      "justification": "Automated assessment based on multi-source impact analysis and framework criteria.",
      "sourceLabel": "Google Trends",
      "sourceReliability": "Unofficial",
      "intelligenceType": "Direct",
      "corroborated": true,
      "startTiming": "14:00",
      "endTiming": "",
      "synthesis": "Evidence shows localized environmental stress and reported infrastructure failure based on emerging reports.",
      "confidenceStatement": "This is a Medium confidence assessment."
    }
  },
  {
    "id": "ev-google-trends-5",
    "lat": 54.5,
    "lng": -2,
    "category": "google-trends",
    "severity": "minor",
    "timestamp": "2025-11-13T17:06:02.403Z",
    "title": "SEARCH SPIKE: \"flood insurance\"",
    "locationName": "Regional | County | Constituency Placeholder",
    "source": "Google Trends",
    "sourceUrl": "#",
    "assessment": {
      "confidenceLabel": "High",
      "confidenceColor": "#4ade80",
      "confidence": 86,
      "justification": "Automated assessment based on multi-source impact analysis and framework criteria.",
      "sourceLabel": "Google Trends",
      "sourceReliability": "Unofficial",
      "intelligenceType": "Direct",
      "corroborated": false,
      "startTiming": "17:00",
      "endTiming": "",
      "synthesis": "Evidence shows localized environmental stress and reported infrastructure failure based on emerging reports.",
      "confidenceStatement": "This is a High confidence assessment."
    }
  },
  {
    "id": "ev-google-trends-6",
    "lat": 54.5,
    "lng": -2,
    "category": "google-trends",
    "severity": "minor",
    "timestamp": "2025-11-13T14:45:50.248Z",
    "title": "SEARCH SPIKE: \"flood insurance\"",
    "locationName": "Regional | County | Constituency Placeholder",
    "source": "Google Trends",
    "sourceUrl": "#",
    "assessment": {
      "confidenceLabel": "Medium",
      "confidenceColor": "#facc15",
      "confidence": 76,
      "justification": "Automated assessment based on multi-source impact analysis and framework criteria.",
      "sourceLabel": "Google Trends",
      "sourceReliability": "Unofficial",
      "intelligenceType": "Direct",
      "corroborated": true,
      "startTiming": "17:00",
      "endTiming": "",
      "synthesis": "Evidence shows localized environmental stress and reported infrastructure failure based on emerging reports.",
      "confidenceStatement": "This is a Medium confidence assessment."
    }
  },
  {
    "id": "ev-google-trends-7",
    "lat": 54.5,
    "lng": -2,
    "category": "google-trends",
    "severity": "severe",
    "timestamp": "2025-11-14T15:51:30.813Z",
    "title": "SEARCH SPIKE: \"flood insurance\"",
    "locationName": "Regional | County | Constituency Placeholder",
    "source": "Google Trends",
    "sourceUrl": "#",
    "assessment": {
      "confidenceLabel": "Medium",
      "confidenceColor": "#facc15",
      "confidence": 81,
      "justification": "Automated assessment based on multi-source impact analysis and framework criteria.",
      "sourceLabel": "Google Trends",
      "sourceReliability": "Unofficial",
      "intelligenceType": "Direct",
      "corroborated": false,
      "startTiming": "15:00",
      "endTiming": "",
      "synthesis": "Evidence shows localized environmental stress and reported infrastructure failure based on emerging reports.",
      "confidenceStatement": "This is a Medium confidence assessment."
    }
  },
  {
    "id": "ev-google-trends-8",
    "lat": 54.5,
    "lng": -2,
    "category": "google-trends",
    "severity": "minor",
    "timestamp": "2025-11-14T11:08:03.256Z",
    "title": "SEARCH SPIKE: \"water pumps\"",
    "locationName": "Regional | County | Constituency Placeholder",
    "source": "Google Trends",
    "sourceUrl": "#",
    "assessment": {
      "confidenceLabel": "Medium",
      "confidenceColor": "#facc15",
      "confidence": 80,
      "justification": "Automated assessment based on multi-source impact analysis and framework criteria.",
      "sourceLabel": "Google Trends",
      "sourceReliability": "Unofficial",
      "intelligenceType": "Direct",
      "corroborated": true,
      "startTiming": "15:00",
      "endTiming": "",
      "synthesis": "Evidence shows localized environmental stress and reported infrastructure failure based on emerging reports.",
      "confidenceStatement": "This is a Medium confidence assessment."
    }
  },
  {
    "id": "ev-google-trends-9",
    "lat": 54.5,
    "lng": -2,
    "category": "google-trends",
    "severity": "significant",
    "timestamp": "2025-11-14T12:33:13.708Z",
    "title": "SEARCH SPIKE: \"sandbags\"",
    "locationName": "Regional | County | Constituency Placeholder",
    "source": "Google Trends",
    "sourceUrl": "#",
    "assessment": {
      "confidenceLabel": "Medium",
      "confidenceColor": "#facc15",
      "confidence": 82,
      "justification": "Automated assessment based on multi-source impact analysis and framework criteria.",
      "sourceLabel": "Google Trends",
      "sourceReliability": "Unofficial",
      "intelligenceType": "Direct",
      "corroborated": false,
      "startTiming": "15:00",
      "endTiming": "",
      "synthesis": "Evidence shows localized environmental stress and reported infrastructure failure based on emerging reports.",
      "confidenceStatement": "This is a Medium confidence assessment."
    }
  },
  {
    "id": "ev-google-trends-10",
    "lat": 54.5,
    "lng": -2,
    "category": "google-trends",
    "severity": "minor",
    "timestamp": "2025-11-14T13:01:31.669Z",
    "title": "SEARCH SPIKE: \"sandbags\"",
    "locationName": "Regional | County | Constituency Placeholder",
    "source": "Google Trends",
    "sourceUrl": "#",
    "assessment": {
      "confidenceLabel": "High",
      "confidenceColor": "#4ade80",
      "confidence": 86,
      "justification": "Automated assessment based on multi-source impact analysis and framework criteria.",
      "sourceLabel": "Google Trends",
      "sourceReliability": "Unofficial",
      "intelligenceType": "Direct",
      "corroborated": false,
      "startTiming": "16:00",
      "endTiming": "",
      "synthesis": "Evidence shows localized environmental stress and reported infrastructure failure based on emerging reports.",
      "confidenceStatement": "This is a High confidence assessment."
    }
  },
  {
    "id": "ev-google-trends-11",
    "lat": 54.5,
    "lng": -2,
    "category": "google-trends",
    "severity": "minor",
    "timestamp": "2025-11-14T14:00:01.721Z",
    "title": "SEARCH SPIKE: \"sandbags\"",
    "locationName": "Regional | County | Constituency Placeholder",
    "source": "Google Trends",
    "sourceUrl": "#",
    "assessment": {
      "confidenceLabel": "High",
      "confidenceColor": "#4ade80",
      "confidence": 93,
      "justification": "Automated assessment based on multi-source impact analysis and framework criteria.",
      "sourceLabel": "Google Trends",
      "sourceReliability": "Unofficial",
      "intelligenceType": "Direct",
      "corroborated": false,
      "startTiming": "16:00",
      "endTiming": "",
      "synthesis": "Evidence shows localized environmental stress and reported infrastructure failure based on emerging reports.",
      "confidenceStatement": "This is a High confidence assessment."
    }
  },
  {
    "id": "ev-google-trends-12",
    "lat": 54.5,
    "lng": -2,
    "category": "google-trends",
    "severity": "significant",
    "timestamp": "2025-11-14T14:09:45.067Z",
    "title": "SEARCH SPIKE: \"water pumps\"",
    "locationName": "Regional | County | Constituency Placeholder",
    "source": "Google Trends",
    "sourceUrl": "#",
    "assessment": {
      "confidenceLabel": "Medium",
      "confidenceColor": "#facc15",
      "confidence": 83,
      "justification": "Automated assessment based on multi-source impact analysis and framework criteria.",
      "sourceLabel": "Google Trends",
      "sourceReliability": "Unofficial",
      "intelligenceType": "Direct",
      "corroborated": true,
      "startTiming": "15:00",
      "endTiming": "",
      "synthesis": "Evidence shows localized environmental stress and reported infrastructure failure based on emerging reports.",
      "confidenceStatement": "This is a Medium confidence assessment."
    }
  },
  {
    "id": "ev-google-trends-13",
    "lat": 54.5,
    "lng": -2,
    "category": "google-trends",
    "severity": "minor",
    "timestamp": "2025-11-14T13:41:10.197Z",
    "title": "SEARCH SPIKE: \"sandbags\"",
    "locationName": "Regional | County | Constituency Placeholder",
    "source": "Google Trends",
    "sourceUrl": "#",
    "assessment": {
      "confidenceLabel": "Medium",
      "confidenceColor": "#facc15",
      "confidence": 74,
      "justification": "Automated assessment based on multi-source impact analysis and framework criteria.",
      "sourceLabel": "Google Trends",
      "sourceReliability": "Unofficial",
      "intelligenceType": "Direct",
      "corroborated": true,
      "startTiming": "17:00",
      "endTiming": "",
      "synthesis": "Evidence shows localized environmental stress and reported infrastructure failure based on emerging reports.",
      "confidenceStatement": "This is a Medium confidence assessment."
    }
  },
  {
    "id": "ev-google-trends-14",
    "lat": 54.5,
    "lng": -2,
    "category": "google-trends",
    "severity": "minor",
    "timestamp": "2025-11-14T08:58:48.562Z",
    "title": "SEARCH SPIKE: \"water pumps\"",
    "locationName": "Regional | County | Constituency Placeholder",
    "source": "Google Trends",
    "sourceUrl": "#",
    "assessment": {
      "confidenceLabel": "Medium",
      "confidenceColor": "#facc15",
      "confidence": 71,
      "justification": "Automated assessment based on multi-source impact analysis and framework criteria.",
      "sourceLabel": "Google Trends",
      "sourceReliability": "Unofficial",
      "intelligenceType": "Direct",
      "corroborated": false,
      "startTiming": "16:00",
      "endTiming": "",
      "synthesis": "Evidence shows localized environmental stress and reported infrastructure failure based on emerging reports.",
      "confidenceStatement": "This is a Medium confidence assessment."
    }
  }
]